ra_pickles/__init__.py
ra_pickles/random_access_pickles_reader.py
ra_pickles/random_access_pickles_writer.py
ra_pickles-0.9.1.5.dist-info/METADATA
ra_pickles-0.9.1.5.dist-info/WHEEL
ra_pickles-0.9.1.5.dist-info/top_level.txt
ra_pickles-0.9.1.5.dist-info/RECORD
