Metadata-Version: 2.1
Name: ra-pickles
Version: 0.9.1.5
Summary: A simple package that allows creating a pickles dataset and fast random access
Home-page: https://github.com/shahrukhqasim/ra_pickles
Author: Shah Rukh Qasim
Author-email: shah.rukh.qasim@cern.ch
License: MIT License
Requires-Dist: numpy
Requires-Dist: tqdm
